{
    "Soon": "Fun / Games Commands Soon in V2 / in Discord.js v13 ",
    "Fast" : [ 
        {
            "qus" : "البرازيل",
            "ans" : ["البرازيل"]
        },
        {
            "qus" : "فلسطين",
            "ans" : ["فلسطين"]
        },
        {
            "qus" : "القسطنطينية",
            "ans" : ["القسطنطينية"]
        },
        {
            "qus" : "النهاية",
            "ans" : ["النهاية"]
        },
        {
            "qus" : "امازون",
            "ans" : ["امازون"]
        },
        {
            "qus" : "جافاسكربت",
            "ans" : ["جافاسكربت"]
        },
        {
            "qus" : "سهله مو صعبه",
            "ans" : ["سهله مو صعبه"]
        },
        {
            "qus" : "طبق رطب مرق بقر",
            "ans" : ["طبق رطب مرق بقر"]
        },
        {
            "qus" : "كينجمان",
            "ans" : ["كينجمان"]
        },
        {
            "qus" : "متجر",
            "ans" : ["متجر"]
        },
        {
            "qus" : "شجرة الأوغيري",
            "ans" : ["شجرة الأوغيري"]
        },
        {
            "qus" : "عش العصفور",
            "ans" : ["عش العصفور"]
        },
        {
            "qus" : "قم بكتابة",
            "ans" : ["قم بكتابة"]
        },
        {
            "qus" : "كانيكي",
            "ans" : ["كانيكي"]
        },
        {
            "qus" : "انا عراسي ريشة",
            "ans" : ["انا عراسي ريشة"]
        },
        {
            "qus" : "KINGMAN",
            "ans" : ["KINGMAN"]
        },
        {
            "qus" : "شو لون السماء",
            "ans" : ["شو لون السماء"]
        },
        {
            "qus" : "كيف حالك",
            "ans" : ["كيف حالك"]
        },
        {
            "qus" : "سوزوكي",
            "ans" : ["سوزوكي"]
        },
        {
            "qus" : "فيراري",
            "ans" : ["فيراري"]
        },
        {
            "qus" : "نحب كينجمان",
            "ans" : ["نحب كينجمان"]
        }
    ],
    "Fkk" : [
        {
            "qus" : "ف ل س ط ي ن",
            "ans" : ["قلسطين"]
        },
        {
            "qus" : "ك ي ن ج م ا ن",
            "ans" : ["كينجمان"]
        },
        {
            "qus" : "ج ا ف ا س ك ر ب ت",
            "ans" : ["جافاسكربت"]
        },
        {
            "qus" : "م ا ي ك ر و س ك و ب",
            "ans" : ["مايكروسكوب"]
        },
        {
            "qus" : "م و س و ع ة",
            "ans" : ["موسوعة"]
        },
        {
            "qus" : "ا ف ل ا م",
            "ans" : ["افلام"]
        },
        {
            "qus" : "ح ا س و ب ا ح ت ر ا ف ي",
            "ans" : ["حاسوب احترافي"]
        },
        {
            "qus" : "ا ل ب ر ا ز ي ل",
            "ans" : ["البرازيل"]
        },
        {
            "qus" : "ف ي ر ا ر ي",
            "ans" : ["فيراري"]
        },
        {
            "qus" : "ب و ج ا ت ي",
            "ans" : ["بوجاتي"]
        },
        {
            "qus" : "ا ل س ع و د ي ة",
            "ans" : ["السعودية"]
        },
        {
            "qus" : "ب ا ي ث و ن",
            "ans" : ["بايثون"]
        },
        {
            "qus" : "س ه ل ه م و ص ع ب ه",
            "ans" : ["سهله مو صعبه"]
        },
        {
            "qus" : "ا ل ن ه ا ي ة ",
            "ans" : ["النهاية"]
        },
        {
            "qus" : "س ا ل ف ة ح ل و ة ",
            "ans" : ["سالفة حلوة"]
        },
        {
            "qus" : "ا ح ب ك",
            "ans" : ["احبك"]
        },
        {
            "qus" : "ت ص ا م ي م",
            "ans" : ["تصاميم"]
        },
        {
            "qus" : "ي و ت ي و ب",
            "ans" : ["يوتيوب"]
        },
        {
            "qus" : "O M G M A N ",
            "ans" : ["OMG MAN"]
        },
        {
            "qus" : "ا ل ق د س",
            "ans" : ["القدس"]
        },
        {
            "qus" : "ع م ا ن",
            "ans" : ["عمان"]
        },
        {
            "qus" : "م س ق ط",
            "ans" : ["مسقط"]
        }
    ],
    "Capitals": [
        {
            "qus" : "لبنان",
            "ans" : ["بيروت"]
        },
        {
            "qus" : "العراق",
            "ans" : ["بغداد"]
        },
        {
            "qus" : "مصر",
            "ans" : ["القاهرة"]
        },
        {
            "qus" : "سوريا",
            "ans" : ["دمشق"]
        },
        {
            "qus" : "السعودية",
            "ans" : ["الرياض"]
        },
        {
            "qus" : "اليمن",
            "ans" : ["صنعاء"]
        },
        {
            "qus" : "السودان",
            "ans" : ["الخرطوم"]
        },
        {
            "qus" : "الاردن",
            "ans" : ["عمان"]
        },
        {
            "qus" : "الإمارات",
            "ans" : ["أبو ظبي","ابوظبي"]
        },
        {
            "qus" : "ليبيا",
            "ans" : ["طرابلس"]
        },
        {
            "qus" : "المغرب",
            "ans" : ["الرباط"]
        },
        {
            "qus" : "فلسطين",
            "ans" : ["القدس"]
        },
        {
            "qus" : "تونس",
            "ans" : ["تونس"]
        },
        {
            "qus" : "الكويت",
            "ans" : ["الكويت"]
        },
        {
            "qus" : "عمان",
            "ans" : ["مسقط"]
        },
        {
            "qus" : "الجزائر",
            "ans" : ["الجزائر"]
        },
        {
            "qus" : "قطر",
            "ans" : ["الدوحة"]
        }
    ],
    "Quzz":[
        {
            "qus" : "مكان تواجد عضو البنكرياس",
            "ans" : ["وراء المعدة","خلف المعدة","المعدة"]
        },        {
            "qus" : "هنالك حيوان يتشارك مع الإنسان في مرض الحصبة، فما هو",
            "ans" : ["القرد"]
        },        {
            "qus" : "أين يبدأ هضم مادة الكربوهيدرات؟",
            "ans" : ["الفم"]
        },        {
            "qus" : "اليوم الذي خلق فيه سيدنا آدم عليه السلام، هو",
            "ans" : ["الجمعة"]
        },        {
            "qus" : "شيء ما ينبض بدون قلب",
            "ans" : ["الساعة"]
        },        {
            "qus" : "ما هو الشيء الذي إذا شلنا الحرف الأوّل منه طار",
            "ans" : ["قطار","مطار"]
        },        {
            "qus" : "من يكون أخو عمك وليس عمك فمن هو",
            "ans" : ["ابوي","أبي"]
        },        {
            "qus" : "شيء ما نراه ولا نستطيع لمسه، أول حروفه شيء يقتل، وآخر حروفه شيء يُشرب فما هو",
            "ans" : ["السماء"]
        },        {
            "qus" : "ما هو الشيء الذي تحمله وفي نفس الوقت يحملك",
            "ans" : ["الحذاء"]
        },        {
            "qus" : "ما هو الشيء الذي تشتريه بمالك ولكن لا تستطيع إدخاله بيتك فما هو",
            "ans" : ["السيارة"]
        }, 
        {
            "qus" : "أحد أنواع الطيور التي تلد ولا تبيض",
            "ans" : ["الخفاش"]
        }, 
        {
            "qus" : "على أي شكل يوجد الأوكسجين في الطبيعة",
            "ans" : ["على شكل جزيئات"]
        }, 
        {
            "qus" : " من هو العالم الذي اكتشف النظرية النسبية",
            "ans" : ["أينشتاين"]
        }
    ]
}